falcon_sync/__init__.py
falcon_sync/version.py
falcon_sync/asgi/__init__.py
falcon_sync/wsgi/__init__.py
falcon_sync/wsgi/adapter.py
falcon_sync/wsgi/protocol.py
tests/wsgi/test_basic.py
falcon_sync-0.0.1.dist-info/LICENSE
falcon_sync-0.0.1.dist-info/METADATA
falcon_sync-0.0.1.dist-info/WHEEL
falcon_sync-0.0.1.dist-info/top_level.txt
falcon_sync-0.0.1.dist-info/RECORD
